pylint_boxwisemaatwerk/__init__.py
pylint_boxwisemaatwerk/boxwise_plugin.py
pylint_boxwisemaatwerk/monkeypatch.py
pylint_boxwisemaatwerk/monkeypatch2.py
pylint_boxwisemaatwerk/augmentations/__init__.py
pylint_boxwisemaatwerk/checkers/__init__.py
pylint_boxwisemaatwerk/checkers/add_reference_checker.py
pylint_boxwisemaatwerk/checkers/function_type_checker.py
pylint_boxwisemaatwerk/checkers/function_variable_checker.py
tests/__init__.py
tests/testsubject.py
tests/unittest_checker_addreference.py
tests/unittest_checker_jedi.py
tests/unittest_monkeypatch2_missingImports.py
tests/stubs/EmitMapper.py
tests/stubs/NCrontab.py
tests/stubs/__init__.py
tests/stubs/clr.py
tests/stubs/Wms/__init__.py
tests/stubs/Wms/RemotingImplementation/__init__.py
pylint_boxwisemaatwerk-1.1.5.dist-info/LICENSE
pylint_boxwisemaatwerk-1.1.5.dist-info/METADATA
pylint_boxwisemaatwerk-1.1.5.dist-info/WHEEL
pylint_boxwisemaatwerk-1.1.5.dist-info/top_level.txt
pylint_boxwisemaatwerk-1.1.5.dist-info/RECORD
