Metadata-Version: 2.1
Name: pylint-boxwisemaatwerk
Version: 1.1.5
Summary: A Pylint plugin to help Pylint understand the boxwise maatwerk framework
Home-page: https://bitbucket.org/tranconbv/pylint-boxwisemaatwerk
Author: Kevin Pawiroredjo, Ana Caires
Author-email: k.pawiroredjo@trancon.nl
License: CLOSED
Keywords: pylint,boxwise,plugin
Platform: UNKNOWN
Classifier: Environment :: Console
Classifier: Intended Audience :: Developers
Classifier: Operating System :: Unix
Classifier: Topic :: Software Development :: Quality Assurance
Classifier: Programming Language :: Python :: 2.7
Requires-Dist: pylint (>=1.9.4)
Requires-Dist: pylint-plugin-utils (>=0.5)
Requires-Dist: astroid (>=1.6.6)
Requires-Dist: jedi
Provides-Extra: for_tests
Requires-Dist: coverage ; extra == 'for_tests'
Requires-Dist: pytest ; extra == 'for_tests'
